[
  {
    "algorithm_name": "DecisionTreeClassifier",
    "algorithm_type": "Classification",
    "accuracy_score": "0.9193548387096774",
    "precision_score": "0.93",
    "recall_score": "0.92",
    "f1_score": "0.91",
    "support": "62"
  },

  {
    "algorithm_name": "KNNClassifier",
    "algorithm_type": "Classification",
    "accuracy_score": "0.6097560975609756",
    "precision_score": "0.53",
    "recall_score": "0.61",
    "f1_score": "0.54",
    "support": "62"
  },

  {
    "algorithm_name": "LogisticRegression",
    "algorithm_type": "Regression",
    "accuracy_score": "0.7886178861788617",
    "precision_score": "0.82",
    "recall_score": "0.79",
    "f1_score": "0.76",
    "support": "62"
  },

  {
    "algorithm_name": "NaiveBayes",
    "algorithm_type": "Regression",
    "accuracy_score": "0.7804878048780488",
    "precision_score": "0.81",
    "recall_score": "0.78",
    "f1_score": "0.75",
    "support": "62"
  },

  {
    "algorithm_name": "RandomForestClassifier",
    "algorithm_type": "Classification",
    "accuracy_score": "0.8548387096774194",
    "precision_score": "0.85",
    "recall_score": "0.85",
    "f1_score": "0.85",
    "support": "62"
  },
  {
    "algorithm_name": "SupportVectorClassifier",
    "algorithm_type": "Classification",
    "accuracy_score": "0.9193548387096774",
    "precision_score": "0.93",
    "recall_score": "0.92",
    "f1_score": "0.91",
    "support": "62"
  },
  {
    "algorithm_name": "RandomForestRegressor",
    "algorithm_type": "Regression",
    "accuracy_score": "0.7804878048780488",
    "precision_score": "0.83",
    "recall_score": "0.79",
    "f1_score": "0.76",
    "support": "62"
  }
]
